Niuke2021HulianwangXiaozhaoKaiguaGonglveChanpinYunyingPianFix1/README.md
Niuke2021HulianwangXiaozhaoKaiguaGonglveChanpinYunyingPianFix1/__init__.py
Niuke2021HulianwangXiaozhaoKaiguaGonglveChanpinYunyingPianFix1/__main__.py
Niuke2021HulianwangXiaozhaoKaiguaGonglveChanpinYunyingPianFix1/file.pdf
Niuke2021HulianwangXiaozhaoKaiguaGonglveChanpinYunyingPianFix1/index.html
niuke_2021_hulianwang_xiaozhao_kaigua_gonglve_chanpin_yunying_pian_fix1-2025.3.25.1.dist-info/METADATA
niuke_2021_hulianwang_xiaozhao_kaigua_gonglve_chanpin_yunying_pian_fix1-2025.3.25.1.dist-info/WHEEL
niuke_2021_hulianwang_xiaozhao_kaigua_gonglve_chanpin_yunying_pian_fix1-2025.3.25.1.dist-info/entry_points.txt
niuke_2021_hulianwang_xiaozhao_kaigua_gonglve_chanpin_yunying_pian_fix1-2025.3.25.1.dist-info/top_level.txt
niuke_2021_hulianwang_xiaozhao_kaigua_gonglve_chanpin_yunying_pian_fix1-2025.3.25.1.dist-info/RECORD
