Metadata-Version: 2.1
Name: niuke-2021-hulianwang-xiaozhao-kaigua-gonglve-chanpin-yunying-pian-fix1
Version: 2025.3.25.1
Summary: 牛客 2021 互联网校招开挂攻略产品运营篇
Home-page: https://github.com/apachecn/niuke-2021-hulianwang-xiaozhao-kaigua-gonglve-chanpin-yunying-pian-fix1
Author: ApacheCN
Author-email: apachecn@163.com
Classifier: Development Status :: 4 - Beta
Classifier: Environment :: Console
Classifier: Intended Audience :: Developers
Classifier: Intended Audience :: End Users/Desktop
Classifier: License :: Other/Proprietary License
Classifier: Natural Language :: Chinese (Simplified)
Classifier: Natural Language :: English
Classifier: Operating System :: OS Independent
Classifier: Programming Language :: Python :: 3
Classifier: Programming Language :: Python :: 3 :: Only
Classifier: Programming Language :: Python :: 3.6
Classifier: Programming Language :: Python :: 3.7
Classifier: Topic :: Text Processing :: Markup :: Markdown
Classifier: Topic :: Text Processing :: Markup :: HTML
Classifier: Topic :: Internet :: WWW/HTTP
Classifier: Topic :: Software Development :: Documentation
Classifier: Topic :: Documentation
Requires-Python: >=3.6
